src/__init__.py
src/node.py
src/trie.py
trie_gnolano-0.0.1.dist-info/METADATA
trie_gnolano-0.0.1.dist-info/WHEEL
trie_gnolano-0.0.1.dist-info/license_files/LICENSE
trie_gnolano-0.0.1.dist-info/RECORD
