Metadata-Version: 2.1
Name: trie-gnolano
Version: 0.0.1
Summary: A small package for trie structures
Project-URL: Bug Tracker, https://github.com/Nolanogenn/trie/issues
Project-URL: Homepage, https://github.com/Nolanogenn/trie
Author-email: Gennaro Nolano <nolanogenn@gmail.com>
License: Copyright (c) 2018 The Python Packaging Authority
Classifier: License :: OSI Approved :: MIT License
Classifier: Operating System :: OS Independent
Classifier: Programming Language :: Python :: 3
Requires-Python: >=3.7
